eBot/GUI.py
eBot/Locator_EKF.py
eBot/__init__.py
eBot/blue_test.py
eBot/eBot.py
eBot/eBotWs.py
eBot/heading_Test.py
eBot/rotate.py
eBot/samplev1.py
eBot/straight_line.py
eBot/util.py
eBot/serial/__init__.py
eBot/serial/serialposix.py
eBot/serial/serialutil.py
eBot/serial/serialwin32.py
firebase/__init__.py
firebase/firebase.py
form/__init__.py
form/common.py
form/formulae.py
form/listener.py
form/main.py
form/parallel.py
form/settings.py
form/spicy.py
form/widgets.py
libdw/__init__.py
libdw/basicGridMap.py
libdw/bayesMap.py
libdw/boundarySM.py
libdw/cc.py
libdw/circ.py
libdw/circuitConnect.py
libdw/coloredHall.py
libdw/colors.py
libdw/corruptInput.py
libdw/dist.py
libdw/distPlot.py
libdw/dw.py
libdw/dynamicCountingGridMap.py
libdw/dynamicGridMap.py
libdw/dynamicMoveToPoint.py
libdw/eBotsonarDist.py
libdw/eyeServo.py
libdw/fr.py
libdw/gauss.py
libdw/gfx.py
libdw/gridDynamics.py
libdw/gridDynamicsWithAngle.py
libdw/gridMap.py
libdw/gw.py
libdw/idealReadings.py
libdw/io.py
libdw/layout.py
libdw/le.py
libdw/leNumpy.py
libdw/lineLocalize.py
libdw/ltism.py
libdw/mapMaker.py
libdw/move.py
libdw/nlcc.py
libdw/nleNumpy.py
libdw/noInput.py
libdw/oneStep.py
libdw/optimize.py
libdw/poly.py
libdw/pyrebase.py
libdw/replanner.py
libdw/replannerRace.py
libdw/se.py
libdw/seFast.py
libdw/seGraphics.py
libdw/search.py
libdw/searchTest.py
libdw/sf.py
libdw/sig.py
libdw/simulate.py
libdw/sm.py
libdw/soarWorld.py
libdw/sonarDist.py
libdw/ssm.py
libdw/threeSteps.py
libdw/tk.py
libdw/ts.py
libdw/ucSearch.py
libdw/util.py
libdw/windows.py
soar/__init__.py
soar/application.py
soar/graphing.py
soar/runsoar.py
soar/util.py
soar/v_oscillo.py
soar/version.py
soar/widgets.py
soar/controls/__init__.py
soar/controls/brain.py
soar/controls/joystick.py
soar/graphics/Amigosonarmonitor.py
soar/graphics/__init__.py
soar/graphics/eBotConnect.py
soar/graphics/eBotConnect_BACKUP.py
soar/graphics/scope.py
soar/graphics/scopeConfig.py
soar/graphics/sonarmonitor.py
soar/io/__init__.py
soar/io/io.py
libdw-4.3.0.dist-info/METADATA
libdw-4.3.0.dist-info/WHEEL
libdw-4.3.0.dist-info/top_level.txt
libdw-4.3.0.dist-info/RECORD
