Metadata-Version: 2.1
Name: libdw
Version: 4.3.0
Summary: The Digital World Code Distribution
Home-page: http://www.sutd.edu.sg
Author: Oka Kurniawan
Author-email: oka_kurniawan@sutd.edu.sg
License: MIT
Keywords: simulation library package
Platform: UNKNOWN
Classifier: Development Status :: 4 - Beta
Classifier: Intended Audience :: Education
Classifier: Topic :: Education
Classifier: License :: OSI Approved :: MIT License
Classifier: Programming Language :: Python :: 3
Requires-Python: >=3
Requires-Dist: requests
Requires-Dist: gcloud
Requires-Dist: oauth2client
Requires-Dist: requests-toolbelt
Requires-Dist: python-jwt
Requires-Dist: sseclient
